pyaes256/__init__.py
pyaes256/__main__.py
pyaes256/common.py
pyaes256/decrypt.py
pyaes256/encrypt.py
pyaes256/paper_wallet.py
pyaes256/templates/printTemplate.md
pyaes256/templates/styles.css
pyaes256-0.3.11.dist-info/LICENSE
pyaes256-0.3.11.dist-info/METADATA
pyaes256-0.3.11.dist-info/WHEEL
pyaes256-0.3.11.dist-info/entry_points.txt
pyaes256-0.3.11.dist-info/top_level.txt
pyaes256-0.3.11.dist-info/RECORD
