Metadata-Version: 2.1
Name: pyaes256
Version: 0.3.11
Summary: Encrypt text with AES256 and create a pdf with QR code that can be printed and stored
Home-page: https://github.com/The-Crocop/pyaes256
Author: Marko Nalis
Author-email: marko@nalis.dev
License: MIT
Platform: UNKNOWN
Requires-Dist: markdown
Requires-Dist: pillow
Requires-Dist: qrcode
Requires-Dist: weasyprint
Requires-Dist: cairocffi
Requires-Dist: pycryptodome
